{
    "6": {
        "food": [ { "brand": "SHOPEE", "title": "美食優惠...", "desc": "...", "url": "...", "time": "10:00" } ],
        "life": [],
        "travel": [],
        "credit": []
    },
    "news": [
        { "brand": "遠見", "title": "...", "url": "...", "time": "08:00", "desc": "最新財經趨勢" }
    ],
    "lounge": {
        "日本": {
            "成田機場": "https://i.imgur.com/...",
            "羽田機場": "https://i.imgur.com/..."
        },
        "泰國": {
            "蘇凡納布機場": "https://i.imgur.com/..."
        }
    }
}
